aioconfig/__init__.py
aioconfig/database.py
aioconfig/storage.py
aioconfig-0.4.6.dist-info/LICENSE
aioconfig-0.4.6.dist-info/WHEEL
aioconfig-0.4.6.dist-info/METADATA
aioconfig-0.4.6.dist-info/RECORD
