Metadata-Version: 2.1
Name: aioconfig
Version: 0.4.6
Summary: 
Home-page: https://github.com/changyuheng/aioconfig
License: MPL-2.0
Author: Henry Chang
Author-email: mr.changyuheng@gmail.com
Requires-Python: >=3.5,<4.0
Classifier: License :: OSI Approved
Classifier: Programming Language :: Python :: 3
Classifier: Programming Language :: Python :: 3.5
Classifier: Programming Language :: Python :: 3.6
Classifier: Programming Language :: Python :: 3.7
Classifier: Programming Language :: Python :: 3.8
Requires-Dist: dataset (>=1.1.2,<2.0.0)
